eanoui/__init__.py
eanoui/admin.py
eanoui/apps.py
eanoui/forms.py
eanoui/widgets.py
django_eanoui-1.1.2.dist-info/LICENSE
django_eanoui-1.1.2.dist-info/METADATA
django_eanoui-1.1.2.dist-info/WHEEL
django_eanoui-1.1.2.dist-info/top_level.txt
django_eanoui-1.1.2.dist-info/RECORD
